month_picker/MonthPicker.py
month_picker/__init__.py
month_picker/_imports_.py
month_picker/metadata.json
month_picker/month_picker.min.js
month_picker/month_picker.min.js.map
month_picker/package-info.json
month_picker-0.0.1.dist-info/LICENSE
month_picker-0.0.1.dist-info/METADATA
month_picker-0.0.1.dist-info/WHEEL
month_picker-0.0.1.dist-info/top_level.txt
month_picker-0.0.1.dist-info/RECORD
