Metadata-Version: 2.1
Name: month_picker
Version: 0.0.1
Summary: Project Description
Home-page: UNKNOWN
Author: Tijs Teulings <tijs.teulings@ecorys.com>
License: MIT
Platform: UNKNOWN
Classifier: Framework :: Dash
License-File: LICENSE
